windows_audio_control-0.1.0.dist-info/METADATA
windows_audio_control-0.1.0.dist-info/WHEEL
windows_audio_control/py.typed
windows_audio_control/_native.pyi
windows_audio_control/__init__.py
windows_audio_control/_native.cp311-win_amd64.pyd
windows_audio_control-0.1.0.dist-info/RECORD
