Metadata-Version: 2.1
Name: windows-audio-control
Version: 0.1.0
Classifier: Programming Language :: Rust
Classifier: Programming Language :: Python :: Implementation :: CPython
Classifier: Programming Language :: Python :: Implementation :: PyPy
Requires-Dist: pytest >= 7; extra == 'tests'
Requires-Dist: pytest-asyncio; extra == 'tests'
Requires-Dist: black; extra == 'tests'
Requires-Dist: coverage; extra == 'tests'
Provides-Extra: tests
Requires-Python: >=3.7
